kaq_quant_common/__init__.py
kaq_quant_common/api/__init__.py
kaq_quant_common/api/common/__init__.py
kaq_quant_common/api/common/api_interface.py
kaq_quant_common/api/common/auth.py
kaq_quant_common/api/rest/__init__.py
kaq_quant_common/api/rest/api_client_base.py
kaq_quant_common/api/rest/api_server_base.py
kaq_quant_common/api/rest/instruction/helper/commission_helper.py
kaq_quant_common/api/rest/instruction/helper/mock_order_helper.py
kaq_quant_common/api/rest/instruction/helper/order_helper.py
kaq_quant_common/api/rest/instruction/instruction_client.py
kaq_quant_common/api/rest/instruction/instruction_server_base.py
kaq_quant_common/api/rest/instruction/models/__init__.py
kaq_quant_common/api/rest/instruction/models/account.py
kaq_quant_common/api/rest/instruction/models/loan.py
kaq_quant_common/api/rest/instruction/models/order.py
kaq_quant_common/api/rest/instruction/models/position.py
kaq_quant_common/api/rest/instruction/models/transfer.py
kaq_quant_common/api/ws/__init__.py
kaq_quant_common/api/ws/exchange/models.py
kaq_quant_common/api/ws/exchange/ws_exchange_client.py
kaq_quant_common/api/ws/exchange/ws_exchange_server.py
kaq_quant_common/api/ws/instruction/__init__.py
kaq_quant_common/api/ws/instruction/ws_instruction_client.py
kaq_quant_common/api/ws/instruction/ws_instruction_server_base.py
kaq_quant_common/api/ws/models.py
kaq_quant_common/api/ws/ws_client_base.py
kaq_quant_common/api/ws/ws_server_base.py
kaq_quant_common/common/__init__.py
kaq_quant_common/common/ddb_table_monitor.py
kaq_quant_common/common/http_monitor.py
kaq_quant_common/common/modules/funding_rate_helper.py
kaq_quant_common/common/modules/limit_order_helper.py
kaq_quant_common/common/modules/limit_order_symbol_monitor.py
kaq_quant_common/common/modules/limit_order_symbol_monitor_group.py
kaq_quant_common/common/monitor_base.py
kaq_quant_common/common/monitor_group.py
kaq_quant_common/common/redis_table_monitor.py
kaq_quant_common-0.2.17.dist-info/METADATA
kaq_quant_common-0.2.17.dist-info/WHEEL
kaq_quant_common-0.2.17.dist-info/RECORD
