Metadata-Version: 2.4
Name: kaq_quant_common
Version: 0.2.17
Summary: 
Author: kevinfuture
Author-email: liuenbofuture@foxmail.com
Requires-Python: >=3.11, <3.13
Classifier: Programming Language :: Python :: 3
Classifier: Programming Language :: Python :: 3.11
Classifier: Programming Language :: Python :: 3.12
Requires-Dist: aiohttp (>=3.13.2,<4.0.0)
Requires-Dist: certifi (>=2025.11.12,<2026.0.0)
Requires-Dist: cryptography (>=46.0.3,<47.0.0)
Requires-Dist: dagster (==1.11.16)
Requires-Dist: dagster-embedded-elt (==0.27.16)
Requires-Dist: dagster-mysql (==0.27.16)
Requires-Dist: dagster-webserver (==1.11.16)
Requires-Dist: dlt (==1.19.1)
Requires-Dist: dolphindb (>=3.0.4.0,<4.0.0.0)
Requires-Dist: flask (>=3.1.2)
Requires-Dist: loguru (>=0.7.3,<0.8.0)
Requires-Dist: mysql-connector-python (>=9.5.0,<10.0.0)
Requires-Dist: mysqlclient (>=2.2.7,<3.0.0)
Requires-Dist: natsort (>=8.4.0,<9.0.0)
Requires-Dist: plotly (>=6.5.0,<7.0.0)
Requires-Dist: psycopg2-binary (>=2.9.11,<3.0.0)
Requires-Dist: pyarrow (>=21.0.0,<22.0.0)
Requires-Dist: pycryptodome (>=3.23.0)
Requires-Dist: pydantic (>=2.12.5)
Requires-Dist: pyhive (>=0.7.0,<0.8.0)
Requires-Dist: pyyaml (>=6.0.3,<7.0.0)
Requires-Dist: redis (>=6.4.0,<7.0.0)
Requires-Dist: requests (>=2.32.0)
Requires-Dist: requests (>=2.32.5,<3.0.0)
Requires-Dist: retrying (>=1.4.2,<2.0.0)
Requires-Dist: sqlalchemy (>=2.0.44,<3.0.0)
Requires-Dist: thrift (>=0.22.0,<0.23.0)
Requires-Dist: twine (>=6.2.0,<7.0.0)
Requires-Dist: uuid (>=1.30,<2.0)
Requires-Dist: vectorbt (>=0.28.1,<0.29.0)
Requires-Dist: websocket-client (>=1.9.0,<2.0.0)
Requires-Dist: websockets (>=15.0.1)
Requires-Dist: werkzeug (>=3.1.4)
